{
  "$schema": "https://wails.io/schemas/config.v2.json",
  "name": "lingshu",
  "outputfilename": "Lingshu",
  "frontend": {
    "dir": "web/admin",
    "install": "npm install",
    "build": "npm run build:wails",
    "dev": "npm run dev",
    "serve": "npx vite preview --port 5173"
  },
  "assetdir": "web/admin/dist",
  "wailsjsdir": "web/admin/src",
  "author": {
    "name": "Lingshu Team",
    "email": "team@lingshu.dev"
  },
  "info": {
    "companyName": "Lingshu",
    "productName": "灵枢",
    "productVersion": "2.0.0",
    "copyright": "Copyright Lingshu Team",
    "comments": "灵枢本地模型网关桌面版"
  }
}


